brokenaxes.py
brokenaxes-0.6.2.dist-info/METADATA
brokenaxes-0.6.2.dist-info/WHEEL
brokenaxes-0.6.2.dist-info/top_level.txt
brokenaxes-0.6.2.dist-info/RECORD
