Metadata-Version: 2.1
Name: brokenaxes
Version: 0.6.2
Summary: Create broken axes
Home-page: https://github.com/bendichter/brokenaxes
Author: Ben Dichter
Author-email: ben.dichter@gmail.com
Keywords: data visualization
Classifier: Intended Audience :: Science/Research
Classifier: Topic :: Scientific/Engineering
Classifier: Framework :: Matplotlib
Classifier: License :: OSI Approved :: MIT License
Classifier: Programming Language :: Python :: 3.8
Classifier: Programming Language :: Python :: 3.9
Classifier: Programming Language :: Python :: 3.10
Classifier: Programming Language :: Python :: 3.11
Classifier: Programming Language :: Python :: 3.12
Provides-Extra: test
